LFSR_code.v
`timescale 1ns / 1ps

module LFSR_code (

input clk , 
output Q,
input load_enable,
input shift_enable,
input [31:0] seed 

);

reg [31:0] Q_reg;


wire taps ;

always @(posedge clk  )
begin 
    if (load_enable)
    Q_reg <= seed;
    else if (shift_enable)
    Q_reg <= {Q_reg [30:0],taps };
    else 
    Q_reg <=Q_reg ;
end 

assign Q=Q_reg[31] ;
assign taps = Q_reg [31]^(Q_reg[20]^(Q_reg [1]^Q_reg[0]));



endmodule

LFSR_code_tb.v
// LFSR_code_tb.v
`timescale 1ns / 1ps
`include "LFSR_code.v"

module LFSR_code_tb ();
    reg clk;
    wire Q;
    integer f;
    integer i;
    reg load_enable;
    reg shift_enable;
    reg [31:0] seed;
    LFSR_code LFSR_code_tb (.clk(clk), .Q(Q), .load_enable(load_enable), .shift_enable(shift_enable), .seed(seed));

    always begin
        clk = 1'b0;
        #10;
        clk = 1'b1;
        #10;
    end

    initial begin
        f = $fopen("verilog_lfsr_out.txt", "w");
        $dumpfile("LFSR_code_tb.vcd");
        $dumpvars(0, LFSR_code_tb);
        clk = 0;
        seed = 32'h00003039;
        load_enable = 1;
        shift_enable = 0;
        #20;
        load_enable = 0;
        shift_enable = 1;

        for (i = 0; i < 200; i = i + 1) begin
            #20;
            @(posedge clk);
            $fwrite(f, "%b\n", Q);
        end
        $fclose(f);
        $finish;
    end
endmodule // LFSR_TB

LFSR_code_tb.vcd
$date
	Tue Nov 07 04:08:09 2023
$end
$version
	Icarus Verilog
$end
$timescale
	1ps
$end
$scope module LFSR_code_tb $end
$scope module LFSR_code_tb $end
$var wire 1 ! clk $end
$var wire 1 " load_enable $end
$var wire 32 # seed [31:0] $end
$var wire 1 $ shift_enable $end
$var wire 1 % taps $end
$var wire 1 & Q $end
$var reg 32 ' Q_reg [31:0] $end
$upscope $end
$upscope $end
$enddefinitions $end
#0
$dumpvars
bx '
x&
x%
0$
b11000000111001 #
1"
0!
$end
#10000
1%
0&
b11000000111001 '
1!
#20000
0!
1$
0"
#30000
0%
b110000001110011 '
1!
#40000
0!
#50000
1%
b1100000011100110 '
1!
#60000
0!
#70000
b11000000111001101 '
1!
#80000
0!
#90000
0%
b110000001110011011 '
1!
#100000
0!
#110000
1%
b1100000011100110110 '
1!
#120000
0!
#130000
b11000000111001101101 '
1!
#140000
0!
#150000
b110000001110011011011 '
1!
#160000
0!
#170000
b1100000011100110110111 '
1!
#180000
0!
#190000
0%
b11000000111001101101111 '
1!
#200000
0!
#210000
1%
b110000001110011011011110 '
1!
#220000
0!
#230000
b1100000011100110110111101 '
1!
#240000
0!
#250000
0%
b11000000111001101101111011 '
1!
#260000
0!
#270000
1%
b110000001110011011011110110 '
1!
#280000
0!
#290000
b1100000011100110110111101101 '
1!
#300000
0!
#310000
b11000000111001101101111011011 '
1!
#320000
0!
#330000
b110000001110011011011110110111 '
1!
#340000
0!
#350000
b1100000011100110110111101101111 '
1!
#360000
0!
#370000
1&
b11000000111001101101111011011111 '
1!
#380000
0!
#390000
b10000001110011011011110110111111 '
1!
#400000
0!
#410000
0&
b11100110110111101101111111 '
1!
#420000
0!
#430000
b111001101101111011011111111 '
1!
#440000
0!
#450000
0%
b1110011011011110110111111111 '
1!
#460000
0!
#470000
b11100110110111101101111111110 '
1!
#480000
0!
#490000
1%
b111001101101111011011111111100 '
1!
#500000
0!
#510000
b1110011011011110110111111111001 '
1!
#520000
0!
#530000
0%
1&
b11100110110111101101111111110011 '
1!
#540000
0!
#550000
1%
b11001101101111011011111111100110 '
1!
#560000
0!
#570000
b10011011011110110111111111001101 '
1!
#580000
0!
#590000
1%
0&
b110110111101101111111110011011 '
1!
#600000
0!
#610000
0%
b1101101111011011111111100110111 '
1!
#620000
0!
#630000
1%
1&
b11011011110110111111111001101110 '
1!
#640000
0!
#650000
b10110111101101111111110011011101 '
1!
#660000
0!
#670000
0%
0&
b1101111011011111111100110111011 '
1!
#680000
0!
#690000
1%
1&
b11011110110111111111001101110110 '
1!
#700000
0!
#710000
b10111101101111111110011011101101 '
1!
#720000
0!
#730000
1%
0&
b1111011011111111100110111011011 '
1!
#740000
0!
#750000
0%
1&
b11110110111111111001101110110111 '
1!
#760000
0!
#770000
1%
b11101101111111110011011101101110 '
1!
#780000
0!
#790000
b11011011111111100110111011011101 '
1!
#800000
0!
#810000
0%
b10110111111111001101110110111011 '
1!
#820000
0!
#830000
0%
0&
b1101111111110011011101101110110 '
1!
#840000
0!
#850000
0%
1&
b11011111111100110111011011101100 '
1!
#860000
0!
#870000
1%
b10111111111001101110110111011000 '
1!
#880000
0!
#890000
1%
0&
b1111111110011011101101110110001 '
1!
#900000
0!
#910000
0%
1&
b11111111100110111011011101100011 '
1!
#920000
0!
#930000
1%
b11111111001101110110111011000110 '
1!
#940000
0!
#950000
0%
b11111110011011101101110110001101 '
1!
#960000
0!
#970000
1%
b11111100110111011011101100011010 '
1!
#980000
0!
#990000
b11111001101110110111011000110101 '
1!
#1000000
0!
#1010000
0%
b11110011011101101110110001101011 '
1!
#1020000
0!
#1030000
b11100110111011011101100011010110 '
1!
#1040000
0!
#1050000
b11001101110110111011000110101100 '
1!
#1060000
0!
#1070000
b10011011101101110110001101011000 '
1!
#1080000
0!
#1090000
0&
b110111011011101100011010110000 '
1!
#1100000
0!
#1110000
1%
b1101110110111011000110101100000 '
1!
#1120000
0!
#1130000
1%
1&
b11011101101110110001101011000001 '
1!
#1140000
0!
#1150000
0%
b10111011011101100011010110000011 '
1!
#1160000
0!
#1170000
1%
0&
b1110110111011000110101100000110 '
1!
#1180000
0!
#1190000
1&
b11101101110110001101011000001101 '
1!
#1200000
0!
#1210000
0%
b11011011101100011010110000011011 '
1!
#1220000
0!
#1230000
b10110111011000110101100000110110 '
1!
#1240000
0!
#1250000
0%
0&
b1101110110001101011000001101100 '
1!
#1260000
0!
#1270000
1%
1&
b11011101100011010110000011011000 '
1!
#1280000
0!
#1290000
b10111011000110101100000110110001 '
1!
#1300000
0!
#1310000
1%
0&
b1110110001101011000001101100011 '
1!
#1320000
0!
#1330000
1&
b11101100011010110000011011000111 '
1!
#1340000
0!
#1350000
0%
b11011000110101100000110110001111 '
1!
#1360000
0!
#1370000
b10110001101011000001101100011110 '
1!
#1380000
0!
#1390000
1%
0&
b1100011010110000011011000111100 '
1!
#1400000
0!
#1410000
1%
1&
b11000110101100000110110001111001 '
1!
#1420000
0!
#1430000
b10001101011000001101100011110011 '
1!
#1440000
0!
#1450000
0%
0&
b11010110000011011000111100111 '
1!
#1460000
0!
#1470000
1%
b110101100000110110001111001110 '
1!
#1480000
0!
#1490000
b1101011000001101100011110011101 '
1!
#1500000
0!
#1510000
1%
1&
b11010110000011011000111100111011 '
1!
#1520000
0!
#1530000
0%
b10101100000110110001111001110111 '
1!
#1540000
0!
#1550000
0%
0&
b1011000001101100011110011101110 '
1!
#1560000
0!
#1570000
1%
1&
b10110000011011000111100111011100 '
1!
#1580000
0!
#1590000
0%
0&
b1100000110110001111001110111001 '
1!
#1600000
0!
#1610000
1%
1&
b11000001101100011110011101110010 '
1!
#1620000
0!
#1630000
0%
b10000011011000111100111011100101 '
1!
#1640000
0!
#1650000
1%
0&
b110110001111001110111001010 '
1!
#1660000
0!
#1670000
b1101100011110011101110010101 '
1!
#1680000
0!
#1690000
b11011000111100111011100101011 '
1!
#1700000
0!
#1710000
b110110001111001110111001010111 '
1!
#1720000
0!
#1730000
b1101100011110011101110010101111 '
1!
#1740000
0!
#1750000
0%
1&
b11011000111100111011100101011111 '
1!
#1760000
0!
#1770000
b10110001111001110111001010111110 '
1!
#1780000
0!
#1790000
0%
0&
b1100011110011101110010101111100 '
1!
#1800000
0!
#1810000
1&
b11000111100111011100101011111000 '
1!
#1820000
0!
#1830000
b10001111001110111001010111110000 '
1!
#1840000
0!
#1850000
1%
0&
b11110011101110010101111100000 '
1!
#1860000
0!
#1870000
b111100111011100101011111000001 '
1!
#1880000
0!
#1890000
b1111001110111001010111110000011 '
1!
#1900000
0!
#1910000
0%
1&
b11110011101110010101111100000111 '
1!
#1920000
0!
#1930000
1%
b11100111011100101011111000001110 '
1!
#1940000
0!
#1950000
0%
b11001110111001010111110000011101 '
1!
#1960000
0!
#1970000
b10011101110010101111100000111010 '
1!
#1980000
0!
#1990000
1%
0&
b111011100101011111000001110100 '
1!
#2000000
0!
#2010000
b1110111001010111110000011101001 '
1!
#2020000
0!
#2030000
0%
1&
b11101110010101111100000111010011 '
1!
#2040000
0!
#2050000
b11011100101011111000001110100110 '
1!
#2060000
0!
#2070000
b10111001010111110000011101001100 '
1!
#2080000
0!
#2090000
1%
0&
b1110010101111100000111010011000 '
1!
#2100000
0!
#2110000
1%
1&
b11100101011111000001110100110001 '
1!
#2120000
0!
#2130000
0%
b11001010111110000011101001100011 '
1!
#2140000
0!
#2150000
1%
b10010101111100000111010011000110 '
1!
#2160000
0!
#2170000
0&
b101011111000001110100110001101 '
1!
#2180000
0!
#2190000
0%
b1010111110000011101001100011011 '
1!
#2200000
0!
#2210000
0%
1&
b10101111100000111010011000110110 '
1!
#2220000
0!
#2230000
0%
0&
b1011111000001110100110001101100 '
1!
#2240000
0!
#2250000
1%
1&
b10111110000011101001100011011000 '
1!
#2260000
0!
#2270000
0%
0&
b1111100000111010011000110110001 '
1!
#2280000
0!
#2290000
1%
1&
b11111000001110100110001101100010 '
1!
#2300000
0!
#2310000
b11110000011101001100011011000101 '
1!
#2320000
0!
#2330000
b11100000111010011000110110001011 '
1!
#2340000
0!
#2350000
0%
b11000001110100110001101100010111 '
1!
#2360000
0!
#2370000
b10000011101001100011011000101110 '
1!
#2380000
0!
#2390000
0%
0&
b111010011000110110001011100 '
1!
#2400000
0!
#2410000
1%
b1110100110001101100010111000 '
1!
#2420000
0!
#2430000
0%
b11101001100011011000101110001 '
1!
#2440000
0!
#2450000
1%
b111010011000110110001011100010 '
1!
#2460000
0!
#2470000
b1110100110001101100010111000101 '
1!
#2480000
0!
#2490000
1%
1&
b11101001100011011000101110001011 '
1!
#2500000
0!
#2510000
0%
b11010011000110110001011100010111 '
1!
#2520000
0!
#2530000
1%
b10100110001101100010111000101110 '
1!
#2540000
0!
#2550000
0&
b1001100011011000101110001011101 '
1!
#2560000
0!
#2570000
0%
1&
b10011000110110001011100010111011 '
1!
#2580000
0!
#2590000
0%
0&
b110001101100010111000101110110 '
1!
#2600000
0!
#2610000
b1100011011000101110001011101100 '
1!
#2620000
0!
#2630000
1%
1&
b11000110110001011100010111011000 '
1!
#2640000
0!
#2650000
0%
b10001101100010111000101110110001 '
1!
#2660000
0!
#2670000
0&
b11011000101110001011101100010 '
1!
#2680000
0!
#2690000
b110110001011100010111011000100 '
1!
#2700000
0!
#2710000
1%
b1101100010111000101110110001000 '
1!
#2720000
0!
#2730000
1%
1&
b11011000101110001011101100010001 '
1!
#2740000
0!
#2750000
0%
b10110001011100010111011000100011 '
1!
#2760000
0!
#2770000
1%
0&
b1100010111000101110110001000110 '
1!
#2780000
0!
#2790000
0%
1&
b11000101110001011101100010001101 '
1!
#2800000
0!
#2810000
b10001011100010111011000100011010 '
1!
#2820000
0!
#2830000
1%
0&
b10111000101110110001000110100 '
1!
#2840000
0!
#2850000
b101110001011101100010001101001 '
1!
#2860000
0!
#2870000
b1011100010111011000100011010011 '
1!
#2880000
0!
#2890000
0%
1&
b10111000101110110001000110100111 '
1!
#2900000
0!
#2910000
0%
0&
b1110001011101100010001101001110 '
1!
#2920000
0!
#2930000
1%
1&
b11100010111011000100011010011100 '
1!
#2940000
0!
#2950000
b11000101110110001000110100111001 '
1!
#2960000
0!
#2970000
0%
b10001011101100010001101001110011 '
1!
#2980000
0!
#2990000
1%
0&
b10111011000100011010011100110 '
1!
#3000000
0!
#3010000
b101110110001000110100111001101 '
1!
#3020000
0!
#3030000
0%
b1011101100010001101001110011011 '
1!
#3040000
0!
#3050000
1%
1&
b10111011000100011010011100110110 '
1!
#3060000
0!
#3070000
0&
b1110110001000110100111001101101 '
1!
#3080000
0!
#3090000
1%
1&
b11101100010001101001110011011011 '
1!
#3100000
0!
#3110000
b11011000100011010011100110110111 '
1!
#3120000
0!
#3130000
0%
b10110001000110100111001101101111 '
1!
#3140000
0!
#3150000
0%
0&
b1100010001101001110011011011110 '
1!
#3160000
0!
#3170000
1%
1&
b11000100011010011100110110111100 '
1!
#3180000
0!
#3190000
b10001000110100111001101101111001 '
1!
#3200000
0!
#3210000
0%
0&
b10001101001110011011011110011 '
1!
#3220000
0!
#3230000
1%
b100011010011100110110111100110 '
1!
#3240000
0!
#3250000
0%
b1000110100111001101101111001101 '
1!
#3260000
0!
#3270000
1%
1&
b10001101001110011011011110011010 '
1!
#3280000
0!
#3290000
0%
0&
b11010011100110110111100110101 '
1!
#3300000
0!
#3310000
1%
b110100111001101101111001101010 '
1!
#3320000
0!
#3330000
b1101001110011011011110011010101 '
1!
#3340000
0!
#3350000
0%
1&
b11010011100110110111100110101011 '
1!
#3360000
0!
#3370000
1%
b10100111001101101111001101010110 '
1!
#3380000
0!
#3390000
0&
b1001110011011011110011010101101 '
1!
#3400000
0!
#3410000
0%
1&
b10011100110110111100110101011011 '
1!
#3420000
0!
#3430000
0%
0&
b111001101101111001101010110110 '
1!
#3440000
0!
#3450000
b1110011011011110011010101101100 '
1!
#3460000
0!
#3470000
1&
b11100110110111100110101011011000 '
1!
#3480000
0!
#3490000
b11001101101111001101010110110000 '
1!
#3500000
0!
#3510000
b10011011011110011010101101100000 '
1!
#3520000
0!
#3530000
1%
0&
b110110111100110101011011000000 '
1!
#3540000
0!
#3550000
b1101101111001101010110110000001 '
1!
#3560000
0!
#3570000
1%
1&
b11011011110011010101101100000011 '
1!
#3580000
0!
#3590000
0%
b10110111100110101011011000000111 '
1!
#3600000
0!
#3610000
0%
0&
b1101111001101010110110000001110 '
1!
#3620000
0!
#3630000
1%
1&
b11011110011010101101100000011100 '
1!
#3640000
0!
#3650000
b10111100110101011011000000111001 '
1!
#3660000
0!
#3670000
0%
0&
b1111001101010110110000001110011 '
1!
#3680000
0!
#3690000
1%
1&
b11110011010101101100000011100110 '
1!
#3700000
0!
#3710000
0%
b11100110101011011000000111001101 '
1!
#3720000
0!
#3730000
1%
b11001101010110110000001110011010 '
1!
#3740000
0!
#3750000
b10011010101101100000011100110101 '
1!
#3760000
0!
#3770000
0%
0&
b110101011011000000111001101011 '
1!
#3780000
0!
#3790000
b1101010110110000001110011010110 '
1!
#3800000
0!
#3810000
0%
1&
b11010101101100000011100110101100 '
1!
#3820000
0!
#3830000
1%
b10101011011000000111001101011000 '
1!
#3840000
0!
#3850000
1%
0&
b1010110110000001110011010110001 '
1!
#3860000
0!
#3870000
1%
1&
b10101101100000011100110101100011 '
1!
#3880000
0!
#3890000
0%
0&
b1011011000000111001101011000111 '
1!
#3900000
0!
#3910000
0%
1&
b10110110000001110011010110001110 '
1!
#3920000
0!
#3930000
0%
0&
b1101100000011100110101100011100 '
1!
#3940000
0!
#3950000
1&
b11011000000111001101011000111000 '
1!
#3960000
0!
#3970000
b10110000001110011010110001110000 '
1!
#3980000
0!
#3990000
1%
0&
b1100000011100110101100011100000 '
1!
#4000000
0!
#4010000
0%
1&
b11000000111001101011000111000001 '
1!
#4020000
0!
#4030000
b10000001110011010110001110000010 '
1!
